calculadora_codigos/__init__.py
calculadora_codigos/soma.py
calculadora_lib-0.1.0.dist-info/LICENSE
calculadora_lib-0.1.0.dist-info/METADATA
calculadora_lib-0.1.0.dist-info/WHEEL
calculadora_lib-0.1.0.dist-info/top_level.txt
calculadora_lib-0.1.0.dist-info/RECORD
